[
  {
    "count": 2, 
    "name": 0
  }, 
  {
    "count": 2, 
    "name": 1
  }, 
  {
    "count": 2, 
    "name": 2
  }, 
  {
    "count": 1, 
    "name": 3
  }, 
  {
    "count": 3, 
    "name": 4
  }, 
  {
    "count": 1, 
    "name": 5
  }, 
  {
    "count": 1, 
    "name": 6
  }, 
  {
    "count": 1, 
    "name": 8
  }, 
  {
    "count": 1, 
    "name": 9
  }, 
  {
    "count": 2, 
    "name": 11
  }, 
  {
    "count": 2, 
    "name": 12
  }, 
  {
    "count": 1, 
    "name": 13
  }, 
  {
    "count": 2, 
    "name": 14
  }, 
  {
    "count": 2, 
    "name": 15
  }, 
  {
    "count": 3, 
    "name": 16
  }, 
  {
    "count": 2, 
    "name": 17
  }, 
  {
    "count": 1, 
    "name": 19
  }, 
  {
    "count": 2, 
    "name": 20
  }, 
  {
    "count": 2, 
    "name": 21
  }, 
  {
    "count": 4, 
    "name": 22
  }, 
  {
    "count": 3, 
    "name": 23
  }
]